{"images":[{"startdate":"20230412","fullstartdate":"202304120700","enddate":"20230413","url":"/th?id=OHR.EuropeFromISS_EN-US3248706956_1920x1080.jpg&rf=LaDigue_1920x1080.jpg&pid=hp","urlbase":"/th?id=OHR.EuropeFromISS_EN-US3248706956","copyright":"Earth seen from the International Space Station (© Tim Peake/ESA/NASA via Getty Images)","copyrightlink":"https://www.bing.com/search?q=Earth&form=hpcapt&filters=HpDate%3a%2220230412_0700%22","title":"A view that's out of this world","quiz":"/search?q=Bing+homepage+quiz&filters=WQOskey:%22HPQuiz_20230412_EuropeFromISS%22&FORM=HPQUIZ","wp":true,"hsh":"89bebc08da423593f4f9bfa1e3e3a35c","drk":1,"top":1,"bot":1,"hs":[]}],"tooltips":{"loading":"正在加载...","previous":"上一个图像","next":"下一个图像","walle":"此图片不能下载用作壁纸。","walls":"下载今日美图。仅限用作桌面壁纸。"}}